<?xml version="1.0" encoding="utf-8" standalone="yes"?>
<Gesture Name = "cross">
	<Stroke>
		<Point X = "541.2773" Y = "58.54297" T = "0" Pressure = "0" />
		<Point X = "541.2773" Y = "58.54297" T = "0" Pressure = "0" />
		<Point X = "541.2773" Y = "58.54297" T = "0" Pressure = "0" />
		<Point X = "541.2773" Y = "58.54297" T = "0" Pressure = "0" />
		<Point X = "541.2773" Y = "58.54297" T = "0" Pressure = "0" />
		<Point X = "541.2773" Y = "58.54297" T = "0" Pressure = "0" />
		<Point X = "541.2773" Y = "58.54297" T = "0" Pressure = "0" />
		<Point X = "541.2773" Y = "58.54297" T = "0" Pressure = "0" />
		<Point X = "541.2773" Y = "58.54297" T = "0" Pressure = "0" />
		<Point X = "541.2773" Y = "58.54297" T = "0" Pressure = "0" />
		<Point X = "541.2773" Y = "58.54297" T = "0" Pressure = "0" />
		<Point X = "541.2773" Y = "58.54297" T = "0" Pressure = "0" />
		<Point X = "541.2773" Y = "59.6875" T = "0" Pressure = "0" />
		<Point X = "541.2773" Y = "67.66797" T = "0" Pressure = "0" />
		<Point X = "541.2773" Y = "74.82031" T = "0" Pressure = "0" />
		<Point X = "541.2773" Y = "79.78516" T = "0" Pressure = "0" />
		<Point X = "541.2773" Y = "80.49219" T = "0" Pressure = "0" />
		<Point X = "541.6016" Y = "81.14844" T = "0" Pressure = "0" />
		<Point X = "541.9258" Y = "81.14844" T = "0" Pressure = "0" />
		<Point X = "542.25" Y = "81.80469" T = "0" Pressure = "0" />
		<Point X = "542.25" Y = "82.46094" T = "0" Pressure = "0" />
		<Point X = "543.0898" Y = "86.61328" T = "0" Pressure = "0" />
		<Point X = "546.1211" Y = "94.21875" T = "0" Pressure = "0" />
		<Point X = "552.1406" Y = "109.9961" T = "0" Pressure = "0" />
		<Point X = "556.9102" Y = "121.3594" T = "0" Pressure = "0" />
		<Point X = "560.3789" Y = "128.3047" T = "0" Pressure = "0" />
		<Point X = "562.7227" Y = "133.9336" T = "0" Pressure = "0" />
		<Point X = "564.2383" Y = "136.2227" T = "0" Pressure = "0" />
		<Point X = "565.5898" Y = "137.2344" T = "0" Pressure = "0" />
		<Point X = "567.8242" Y = "140.7031" T = "0" Pressure = "0" />
		<Point X = "569.9492" Y = "144.5234" T = "0" Pressure = "0" />
		<Point X = "574.9297" Y = "153.5156" T = "0" Pressure = "0" />
		<Point X = "578.0938" Y = "158.0234" T = "0" Pressure = "0" />
		<Point X = "581.9141" Y = "163.3008" T = "0" Pressure = "0" />
		<Point X = "584.4453" Y = "166.2734" T = "0" Pressure = "0" />
		<Point X = "585.8516" Y = "167.6875" T = "0" Pressure = "0" />
		<Point X = "587.2578" Y = "168.3984" T = "0" Pressure = "0" />
		<Point X = "588.6641" Y = "169.4609" T = "0" Pressure = "0" />
		<Point X = "591.5195" Y = "171.5078" T = "0" Pressure = "0" />
		<Point X = "593.9648" Y = "173.1758" T = "0" Pressure = "0" />
		<Point X = "598.4531" Y = "176.043" T = "0" Pressure = "0" />
		<Point X = "599.5938" Y = "176.8047" T = "0" Pressure = "0" />
		<Point X = "602.6328" Y = "177.9805" T = "0" Pressure = "0" />
		<Point X = "604.4766" Y = "179.0703" T = "0" Pressure = "0" />
		<Point X = "606.7578" Y = "180.5938" T = "0" Pressure = "0" />
		<Point X = "609.0391" Y = "181.7383" T = "0" Pressure = "0" />
		<Point X = "610.8828" Y = "182.8555" T = "0" Pressure = "0" />
		<Point X = "612.2891" Y = "183.5664" T = "0" Pressure = "0" />
		<Point X = "613.6953" Y = "184.2773" T = "0" Pressure = "0" />
		<Point X = "615.9766" Y = "185.4219" T = "0" Pressure = "0" />
		<Point X = "618.75" Y = "186.625" T = "0" Pressure = "0" />
		<Point X = "621.5234" Y = "187.7969" T = "0" Pressure = "0" />
		<Point X = "625.9297" Y = "189.4102" T = "0" Pressure = "0" />
		<Point X = "627.0703" Y = "189.793" T = "0" Pressure = "0" />
		<Point X = "629.3516" Y = "190.5586" T = "0" Pressure = "0" />
		<Point X = "631.6328" Y = "190.5586" T = "0" Pressure = "0" />
		<Point X = "634.1797" Y = "190.9141" T = "0" Pressure = "0" />
		<Point X = "636.0234" Y = "191.2969" T = "0" Pressure = "0" />
		<Point X = "637.8672" Y = "191.6523" T = "0" Pressure = "0" />
		<Point X = "639.2734" Y = "192.0078" T = "0" Pressure = "0" />
		<Point X = "640.6797" Y = "192.3633" T = "0" Pressure = "0" />
		<Point X = "641.707" Y = "192.7188" T = "0" Pressure = "0" />
		<Point X = "643.1133" Y = "193.0742" T = "0" Pressure = "0" />
		<Point X = "644.5195" Y = "193.0742" T = "0" Pressure = "0" />
		<Point X = "645.9258" Y = "193.0742" T = "0" Pressure = "0" />
		<Point X = "647.2773" Y = "193.0742" T = "0" Pressure = "0" />
		<Point X = "647.6016" Y = "193.0742" T = "0" Pressure = "0" />
		<Point X = "648.25" Y = "193.0742" T = "0" Pressure = "0" />
		<Point X = "648.5742" Y = "193.0742" T = "0" Pressure = "0" />
		<Point X = "648.5742" Y = "193.0742" T = "0" Pressure = "0" />
	</Stroke>
	<Stroke>
		<Point X = "402.1797" Y = "128.8086" T = "0" Pressure = "0" />
		<Point X = "402.1797" Y = "128.8086" T = "0" Pressure = "0" />
		<Point X = "402.1797" Y = "128.8086" T = "0" Pressure = "0" />
		<Point X = "402.1797" Y = "128.8086" T = "0" Pressure = "0" />
		<Point X = "402.1797" Y = "128.8086" T = "0" Pressure = "0" />
		<Point X = "402.1797" Y = "128.8086" T = "0" Pressure = "0" />
		<Point X = "402.1797" Y = "128.8086" T = "0" Pressure = "0" />
		<Point X = "402.1797" Y = "128.8086" T = "0" Pressure = "0" />
		<Point X = "402.1797" Y = "128.8086" T = "0" Pressure = "0" />
		<Point X = "402.1797" Y = "128.8086" T = "0" Pressure = "0" />
		<Point X = "402.1797" Y = "128.8086" T = "0" Pressure = "0" />
		<Point X = "402.1797" Y = "128.8086" T = "0" Pressure = "0" />
		<Point X = "402.1797" Y = "128.8086" T = "0" Pressure = "0" />
		<Point X = "402.8828" Y = "128.8086" T = "0" Pressure = "0" />
		<Point X = "407.2969" Y = "128.8086" T = "0" Pressure = "0" />
		<Point X = "412.2578" Y = "128.8086" T = "0" Pressure = "0" />
		<Point X = "419.1953" Y = "128.8086" T = "0" Pressure = "0" />
		<Point X = "428.2813" Y = "128.8086" T = "0" Pressure = "0" />
		<Point X = "436.5938" Y = "129.332" T = "0" Pressure = "0" />
		<Point X = "442.2148" Y = "129.332" T = "0" Pressure = "0" />
		<Point X = "448.4375" Y = "129.332" T = "0" Pressure = "0" />
		<Point X = "455.375" Y = "129.332" T = "0" Pressure = "0" />
		<Point X = "462.1367" Y = "129.332" T = "0" Pressure = "0" />
		<Point X = "467.2109" Y = "129.332" T = "0" Pressure = "0" />
		<Point X = "471.625" Y = "129.332" T = "0" Pressure = "0" />
		<Point X = "478.7656" Y = "130.207" T = "0" Pressure = "0" />
		<Point X = "480.3984" Y = "131.0273" T = "0" Pressure = "0" />
		<Point X = "483.7188" Y = "131.8477" T = "0" Pressure = "0" />
		<Point X = "486.4922" Y = "133.0508" T = "0" Pressure = "0" />
		<Point X = "488.7734" Y = "133.8164" T = "0" Pressure = "0" />
		<Point X = "492.1953" Y = "134.582" T = "0" Pressure = "0" />
		<Point X = "494.9688" Y = "135.375" T = "0" Pressure = "0" />
		<Point X = "497.7422" Y = "136.168" T = "0" Pressure = "0" />
		<Point X = "501.5547" Y = "136.6055" T = "0" Pressure = "0" />
		<Point X = "505.9141" Y = "137.4805" T = "0" Pressure = "0" />
		<Point X = "509.7266" Y = "138.3281" T = "0" Pressure = "0" />
		<Point X = "513.5391" Y = "139.1758" T = "0" Pressure = "0" />
		<Point X = "517.3516" Y = "139.6133" T = "0" Pressure = "0" />
		<Point X = "522.7969" Y = "140.4609" T = "0" Pressure = "0" />
		<Point X = "526.2383" Y = "140.9531" T = "0" Pressure = "0" />
		<Point X = "531.8008" Y = "141.8828" T = "0" Pressure = "0" />
		<Point X = "537.5898" Y = "142.4063" T = "0" Pressure = "0" />
		<Point X = "542.5508" Y = "142.8711" T = "0" Pressure = "0" />
		<Point X = "551.4023" Y = "142.8711" T = "0" Pressure = "0" />
		<Point X = "557.625" Y = "142.8711" T = "0" Pressure = "0" />
		<Point X = "563.1875" Y = "142.8711" T = "0" Pressure = "0" />
		<Point X = "568.75" Y = "142.8711" T = "0" Pressure = "0" />
		<Point X = "573.1641" Y = "142.4102" T = "0" Pressure = "0" />
		<Point X = "578.7266" Y = "141.4883" T = "0" Pressure = "0" />
		<Point X = "583.3086" Y = "140.6211" T = "0" Pressure = "0" />
		<Point X = "588.7539" Y = "139.375" T = "0" Pressure = "0" />
		<Point X = "592.0195" Y = "138.5625" T = "0" Pressure = "0" />
		<Point X = "595.4414" Y = "137.4258" T = "0" Pressure = "0" />
		<Point X = "597.9883" Y = "136.6953" T = "0" Pressure = "0" />
		<Point X = "599.3945" Y = "136.3438" T = "0" Pressure = "0" />
		<Point X = "602.168" Y = "135.9375" T = "0" Pressure = "0" />
		<Point X = "605.4883" Y = "135.125" T = "0" Pressure = "0" />
		<Point X = "608.3711" Y = "134.3398" T = "0" Pressure = "0" />
		<Point X = "611.6367" Y = "133.5273" T = "0" Pressure = "0" />
		<Point X = "616.5977" Y = "131.7305" T = "0" Pressure = "0" />
		<Point X = "619.3711" Y = "130.5352" T = "0" Pressure = "0" />
		<Point X = "623.7852" Y = "128.3281" T = "0" Pressure = "0" />
		<Point X = "628.4102" Y = "124.9531" T = "0" Pressure = "0" />
		<Point X = "631.3594" Y = "122.9883" T = "0" Pressure = "0" />
		<Point X = "633.6953" Y = "121.8203" T = "0" Pressure = "0" />
		<Point X = "635.9766" Y = "120.6836" T = "0" Pressure = "0" />
		<Point X = "638.75" Y = "119.1094" T = "0" Pressure = "0" />
		<Point X = "641.7891" Y = "117.6484" T = "0" Pressure = "0" />
		<Point X = "646.3516" Y = "115.7539" T = "0" Pressure = "0" />
		<Point X = "648.6328" Y = "114.9961" T = "0" Pressure = "0" />
		<Point X = "650.9141" Y = "114.2383" T = "0" Pressure = "0" />
		<Point X = "652.7578" Y = "113.1563" T = "0" Pressure = "0" />
		<Point X = "655.0391" Y = "112.0195" T = "0" Pressure = "0" />
		<Point X = "657.8125" Y = "110.4453" T = "0" Pressure = "0" />
		<Point X = "661.8086" Y = "108.4375" T = "0" Pressure = "0" />
		<Point X = "664.0898" Y = "106.9219" T = "0" Pressure = "0" />
		<Point X = "666.8633" Y = "105.7266" T = "0" Pressure = "0" />
		<Point X = "669.6367" Y = "104.1523" T = "0" Pressure = "0" />
		<Point X = "671.918" Y = "103.0156" T = "0" Pressure = "0" />
		<Point X = "674.1992" Y = "102.2578" T = "0" Pressure = "0" />
		<Point X = "676.043" Y = "101.5273" T = "0" Pressure = "0" />
		<Point X = "678.3789" Y = "100.3594" T = "0" Pressure = "0" />
		<Point X = "680.6602" Y = "99.98047" T = "0" Pressure = "0" />
		<Point X = "682.5039" Y = "99.62891" T = "0" Pressure = "0" />
		<Point X = "683.9102" Y = "99.27734" T = "0" Pressure = "0" />
		<Point X = "686.0195" Y = "98.57422" T = "0" Pressure = "0" />
		<Point X = "687.8633" Y = "97.84375" T = "0" Pressure = "0" />
		<Point X = "689.2695" Y = "97.14063" T = "0" Pressure = "0" />
		<Point X = "691.5508" Y = "96.38281" T = "0" Pressure = "0" />
		<Point X = "693.3945" Y = "96.00391" T = "0" Pressure = "0" />
		<Point X = "696.168" Y = "94.83984" T = "0" Pressure = "0" />
		<Point X = "698.0117" Y = "94.10938" T = "0" Pressure = "0" />
		<Point X = "700.8945" Y = "93.32422" T = "0" Pressure = "0" />
		<Point X = "703.668" Y = "93.32422" T = "0" Pressure = "0" />
		<Point X = "706.4414" Y = "92.91797" T = "0" Pressure = "0" />
		<Point X = "709.707" Y = "92.91797" T = "0" Pressure = "0" />
		<Point X = "712.5898" Y = "92.48438" T = "0" Pressure = "0" />
		<Point X = "716.5039" Y = "92.48438" T = "0" Pressure = "0" />
		<Point X = "718.3477" Y = "92.48438" T = "0" Pressure = "0" />
		<Point X = "719.7539" Y = "92.48438" T = "0" Pressure = "0" />
		<Point X = "720.7813" Y = "92.48438" T = "0" Pressure = "0" />
		<Point X = "721.8086" Y = "92.48438" T = "0" Pressure = "0" />
		<Point X = "722.457" Y = "92.48438" T = "0" Pressure = "0" />
		<Point X = "723.8633" Y = "92.48438" T = "0" Pressure = "0" />
		<Point X = "725.2695" Y = "92.48438" T = "0" Pressure = "0" />
		<Point X = "727.5508" Y = "93.25" T = "0" Pressure = "0" />
		<Point X = "729.3945" Y = "93.98828" T = "0" Pressure = "0" />
		<Point X = "732.168" Y = "94.78125" T = "0" Pressure = "0" />
		<Point X = "734.4492" Y = "95.92578" T = "0" Pressure = "0" />
		<Point X = "736.7852" Y = "96.69141" T = "0" Pressure = "0" />
		<Point X = "739.6563" Y = "97.42969" T = "0" Pressure = "0" />
		<Point X = "740.6289" Y = "97.42969" T = "0" Pressure = "0" />
		<Point X = "740.9531" Y = "97.42969" T = "0" Pressure = "0" />
		<Point X = "741.2773" Y = "97.75781" T = "0" Pressure = "0" />
	</Stroke>
	<Stroke>
		<Point X = "880.5156" Y = "159.418" T = "0" Pressure = "0" />
	</Stroke>
</Gesture>
